{
  "TRV1": {
    "build": {
      "compileArgs": [],
      "ninjaArgs": [],
      "buildDirectoryPath": "build-TRV1",
      "sdkconfigDefaults": [],
      "sdkconfigFilePath": ""
    },
    "env": {
      "CFLAGS": "-DBUILD_FREEHOUSE_MODEL=TRV1"
    },
    "flashBaudRate": "",
    "idfTarget": "",
    "monitorBaudRate": "",
    "openOCD": {
      "debugLevel": -1,
      "configs": [],
      "args": []
    },
    "tasks": {
      "preBuild": "",
      "preFlash": "",
      "postBuild": "",
      "postFlash": ""
    }
  },
  "TRV3": {
    "build": {
      "compileArgs": [],
      "ninjaArgs": [],
      "buildDirectoryPath": "build-TRV3",
      "sdkconfigDefaults": [],
      "sdkconfigFilePath": ""
    },
    "env": {
      "CFLAGS": "-DBUILD_FREEHOUSE_MODEL=TRV3"
    },
    "flashBaudRate": "",
    "idfTarget": "",
    "monitorBaudRate": "",
    "openOCD": {
      "debugLevel": -1,
      "configs": [],
      "args": []
    },
    "tasks": {
      "preBuild": "",
      "preFlash": "",
      "postBuild": "",
      "postFlash": ""
    }
  }
}